simplelogin/cli.py
simplelogin-0.2.5.dist-info/METADATA
simplelogin-0.2.5.dist-info/WHEEL
simplelogin-0.2.5.dist-info/entry_points.txt
simplelogin-0.2.5.dist-info/licenses/LICENSE.md
simplelogin-0.2.5.dist-info/RECORD
