Metadata-Version: 2.4
Name: simplelogin
Version: 0.2.5
Summary: A command-line interface for managing your SimpleLogin email aliases and custom domains.
Project-URL: Homepage, https://github.com/joedemcher/simplelogin-cli
Project-URL: Issues, https://github.com/joedemcher/simplelogin-cli/issues
Project-URL: Documentation, https://github.com/joedemcher/simplelogin-cli/README.md
Author-email: Joseph Demcher <git@joedem.ch>
License-Expression: MIT
License-File: LICENSE.md
Keywords: aliases,cli,email,privacy,simplelogin
Requires-Dist: docopt>=0.6.2
Requires-Dist: pyyaml>=5.4.0
Requires-Dist: questionary>=1.10.0
Requires-Dist: requests>=2.25.0
Requires-Dist: tabulate>=0.8.9
